main.py
setup.py
Next_ViT.egg-info/PKG-INFO
Next_ViT.egg-info/SOURCES.txt
Next_ViT.egg-info/dependency_links.txt
Next_ViT.egg-info/requires.txt
Next_ViT.egg-info/top_level.txt