Metadata-Version: 2.1
Name: Next-ViT
Version: 912.6
Summary: x
Author: x
Author-email: xxx@outlook.com
Requires-Dist: requests
